axlearn/.DS_Store
axlearn/__init__.py
axlearn/audio/__init__.py
axlearn/audio/asr_decoder.py
axlearn/audio/asr_decoder_test.py
axlearn/audio/asr_encoder.py
axlearn/audio/asr_encoder_test.py
axlearn/audio/frontend.py
axlearn/audio/frontend_test.py
axlearn/audio/frontend_utils.py
axlearn/audio/frontend_utils_test.py
axlearn/audio/input_asr.py
axlearn/audio/input_asr_test.py
axlearn/audio/spectrum_augmenter.py
axlearn/audio/spectrum_augmenter_test.py
axlearn/audio/subsamplers.py
axlearn/audio/subsamplers_test.py
axlearn/audio/test_utils.py
axlearn/cli/__init__.py
axlearn/cli/gcp.py
axlearn/cli/utils.py
axlearn/cli/utils_test.py
axlearn/cli/testdata/dummy.py
axlearn/cloud/__init__.py
axlearn/cloud/common/__init__.py
axlearn/cloud/common/bastion.py
axlearn/cloud/common/bastion_test.py
axlearn/cloud/common/bundler.py
axlearn/cloud/common/bundler_test.py
axlearn/cloud/common/cleaner.py
axlearn/cloud/common/config.py
axlearn/cloud/common/config_test.py
axlearn/cloud/common/docker.py
axlearn/cloud/common/job.py
axlearn/cloud/common/job_test.py
axlearn/cloud/common/quota.py
axlearn/cloud/common/quota_test.py
axlearn/cloud/common/scheduler.py
axlearn/cloud/common/scheduler_test.py
axlearn/cloud/common/types.py
axlearn/cloud/common/uploader.py
axlearn/cloud/common/uploader_test.py
axlearn/cloud/common/utils.py
axlearn/cloud/common/utils_test.py
axlearn/cloud/common/writer.py
axlearn/cloud/common/writer_test.py
axlearn/cloud/common/testdata/counter.py
axlearn/cloud/gcp/__init__.py
axlearn/cloud/gcp/bundler.py
axlearn/cloud/gcp/bundler_test.py
axlearn/cloud/gcp/config.py
axlearn/cloud/gcp/config_test.py
axlearn/cloud/gcp/job.py
axlearn/cloud/gcp/job_test.py
axlearn/cloud/gcp/scopes.py
axlearn/cloud/gcp/storage.py
axlearn/cloud/gcp/storage_test.py
axlearn/cloud/gcp/test_utils.py
axlearn/cloud/gcp/tpu.py
axlearn/cloud/gcp/tpu_cleaner.py
axlearn/cloud/gcp/tpu_cleaner_test.py
axlearn/cloud/gcp/tpu_test.py
axlearn/cloud/gcp/utils.py
axlearn/cloud/gcp/utils_test.py
axlearn-0.0.1.post20240213000026.dist-info/entry_points.txt
axlearn-0.0.1.post20240213000026.dist-info/LICENSE
axlearn-0.0.1.post20240213000026.dist-info/WHEEL
axlearn-0.0.1.post20240213000026.dist-info/METADATA
axlearn-0.0.1.post20240213000026.dist-info/RECORD
