Metadata-Version: 2.1
Name: axlearn
Version: 0.0.1.post20240213000026
Summary: AXLearn
Requires-Python: >=3.9
Requires-Dist: attrs>=21.3.0
Requires-Dist: absl-py
Requires-Dist: chex<0.1.81
Requires-Dist: flax==0.7.4
Requires-Dist: importlab==0.7
Requires-Dist: jax==0.4.21
Requires-Dist: jaxlib==0.4.21
Requires-Dist: nltk==3.7
Requires-Dist: numpy<1.24
Requires-Dist: optax==0.1.7
Requires-Dist: portpicker
Requires-Dist: protobuf>=3.20.3
Requires-Dist: tensorboard-plugin-profile==2.14.0
Requires-Dist: tensorflow==2.14.0
Requires-Dist: tensorflow-datasets>=4.9.2
Requires-Dist: tensorflow-io>=0.34.0
Requires-Dist: tensorflow_text==2.14.0; platform_machine == 'x86_64'
Requires-Dist: tensorstore>=0.1.21
Requires-Dist: toml
Requires-Dist: typing-extensions>=4.2.0
Requires-Dist: seqio==0.0.18
Requires-Dist: tensorflow-metal==1.1.0 ; extra == "apple-silicon" and ( platform_machine == 'arm64')
Requires-Dist: apache-beam==2.52.0 ; extra == "dataflow"
Requires-Dist: apache-beam[gcp] ; extra == "dataflow"
Requires-Dist: google-apitools ; extra == "dataflow"
Requires-Dist: orjson==3.9.10 ; extra == "dataflow"
Requires-Dist: black==23.1a1 ; extra == "dev"
Requires-Dist: diffusers==0.16.1 ; extra == "dev"
Requires-Dist: einops ; extra == "dev"
Requires-Dist: evaluate ; extra == "dev"
Requires-Dist: fairseq==0.12.2 ; extra == "dev"
Requires-Dist: isort ; extra == "dev"
Requires-Dist: pre-commit ; extra == "dev"
Requires-Dist: pycocotools ; extra == "dev"
Requires-Dist: pylint==2.13.9 ; extra == "dev"
Requires-Dist: pytest ; extra == "dev"
Requires-Dist: pytest-xdist ; extra == "dev"
Requires-Dist: pytype==2022.4.22 ; extra == "dev"
Requires-Dist: scikit-learn>=1.1.1 ; extra == "dev"
Requires-Dist: scipy ; extra == "dev"
Requires-Dist: sentencepiece != 0.1.92 ; extra == "dev"
Requires-Dist: tqdm ; extra == "dev"
Requires-Dist: timm==0.6.12 ; extra == "dev"
Requires-Dist: torch>=1.12.1 ; extra == "dev"
Requires-Dist: torchvision==0.16.1 ; extra == "dev"
Requires-Dist: transformers==4.37.2 ; extra == "dev"
Requires-Dist: wandb ; extra == "dev"
Requires-Dist: wrapt ; extra == "dev"
Requires-Dist: cloud-tpu-client ; extra == "gcp"
Requires-Dist: crcmod ; extra == "gcp"
Requires-Dist: google-api-python-client==2.109.0 ; extra == "gcp"
Requires-Dist: google-auth==2.23.0 ; extra == "gcp"
Requires-Dist: google-auth[pyopenssl] ; extra == "gcp"
Requires-Dist: pyOpenSSL>=22.1.0 ; extra == "gcp"
Requires-Dist: google-cloud-storage==2.11.0 ; extra == "gcp"
Requires-Dist: google-cloud-core==2.3.3 ; extra == "gcp"
Requires-Dist: axlearn[gcp] ; extra == "tpu"
Requires-Dist: jax[tpu]==0.4.21 ; extra == "tpu"
Requires-Dist: setuptools==65.7.0 ; extra == "vertexai_tensorboard"
Requires-Dist: google-cloud-aiplatform[tensorboard] ; extra == "vertexai_tensorboard"
Requires-Dist: tensorboard ; extra == "vertexai_tensorboard"
Provides-Extra: apple-silicon
Provides-Extra: dataflow
Provides-Extra: dev
Provides-Extra: gcp
Provides-Extra: tpu
Provides-Extra: vertexai_tensorboard
